dependency_injection.py
dependency_injection-1.2.0.dist-info/METADATA
dependency_injection-1.2.0.dist-info/RECORD
dependency_injection-1.2.0.dist-info/WHEEL
dependency_injection-1.2.0.dist-info/top_level.txt
